envarify/__init__.py
envarify/envarify.py
envarify/errors.py
envarify/inspect.py
envarify/parse.py
envarify/py.typed
envarify/types.py
envarify/version.py
envarify-1.5.0.dist-info/licenses/LICENSE
envarify-1.5.0.dist-info/METADATA
envarify-1.5.0.dist-info/WHEEL
envarify-1.5.0.dist-info/top_level.txt
envarify-1.5.0.dist-info/RECORD
