Metadata-Version: 2.4
Name: envarify
Version: 1.5.0
Summary: Environment variables parsing and validation using python type hints
Home-page: https://github.com/vadimtitov/envarify
Author: Vadim Titov
Author-email: titov.hse@gmail.com
Project-URL: Bug Tracker, https://github.com/vadimtitov/envarify/issues
Classifier: Development Status :: 5 - Production/Stable
Classifier: Intended Audience :: Developers
Classifier: License :: OSI Approved :: MIT License
Classifier: Operating System :: OS Independent
Classifier: Programming Language :: Python :: 3.6
Classifier: Programming Language :: Python :: 3.7
Classifier: Programming Language :: Python :: 3.8
Classifier: Programming Language :: Python :: 3.9
Classifier: Programming Language :: Python :: 3.10
Classifier: Programming Language :: Python :: 3.11
Classifier: Programming Language :: Python :: 3.12
Requires-Python: >=3.6
License-File: LICENSE
Provides-Extra: test
Requires-Dist: pytest; extra == "test"
Dynamic: license-file
